potojson/__init__.py
potojson/__main__.py
potojson-2.0.0.dist-info/LICENSE
potojson-2.0.0.dist-info/METADATA
potojson-2.0.0.dist-info/WHEEL
potojson-2.0.0.dist-info/entry_points.txt
potojson-2.0.0.dist-info/top_level.txt
potojson-2.0.0.dist-info/RECORD
