Metadata-Version: 2.1
Name: potojson
Version: 2.0.0
Summary: Pofile to JSON conversion without pain.
Home-page: https://github.com/mondeja/potojson
Author: Álvaro Mondéjar Rubio
Author-email: mondejar1994@gmail.com
License: BSD-3-Clause
Project-URL: Documentation, https://github.com/mondeja/potojson/blob/master/README.md#documentation
Project-URL: GitHub Project, https://github.com/mondeja/potojson
Project-URL: Issue Tracker, https://github.com/mondeja/potojson/issues
Platform: UNKNOWN
Classifier: Development Status :: 4 - Beta
Classifier: License :: OSI Approved :: BSD License
Classifier: Operating System :: OS Independent
Classifier: Programming Language :: Python :: 3
Classifier: Programming Language :: Python :: 3.7
Classifier: Programming Language :: Python :: 3.8
Classifier: Programming Language :: Python :: 3.9
Classifier: Programming Language :: Python :: 3.10
Classifier: Programming Language :: Python :: 3.11
Classifier: Topic :: Software Development :: Internationalization
Classifier: Topic :: Text Processing
Requires-Python: >=3.7
Requires-Dist: polib
Provides-Extra: dev
Requires-Dist: bump2version (==1.0.1) ; extra == 'dev'
Requires-Dist: flake8 (==3.9.2) ; extra == 'dev'
Requires-Dist: flake8-docstrings (==1.6.0) ; extra == 'dev'
Requires-Dist: flake8-implicit-str-concat (==0.2.0) ; extra == 'dev'
Requires-Dist: flake8-print (==4.0.0) ; extra == 'dev'
Requires-Dist: flake8-rst-docstrings (==0.2.3) ; extra == 'dev'
Requires-Dist: isort (==5.9.1) ; extra == 'dev'
Requires-Dist: pre-commit (==2.13.0) ; extra == 'dev'
Requires-Dist: pytest (==6.2.5) ; extra == 'dev'
Requires-Dist: pytest-cov (==3.0.0) ; extra == 'dev'
Requires-Dist: yamllint (==1.26.1) ; extra == 'dev'
Provides-Extra: lint
Requires-Dist: flake8 (==3.9.2) ; extra == 'lint'
Requires-Dist: flake8-docstrings (==1.6.0) ; extra == 'lint'
Requires-Dist: flake8-implicit-str-concat (==0.2.0) ; extra == 'lint'
Requires-Dist: flake8-print (==4.0.0) ; extra == 'lint'
Requires-Dist: flake8-rst-docstrings (==0.2.3) ; extra == 'lint'
Requires-Dist: isort (==5.9.1) ; extra == 'lint'
Requires-Dist: yamllint (==1.26.1) ; extra == 'lint'
Provides-Extra: test
Requires-Dist: pytest (==6.2.5) ; extra == 'test'
Requires-Dist: pytest-cov (==3.0.0) ; extra == 'test'
